{
    "version": "4.0",
    "environment": {
        "generated_model": {
            "model_files": [
                {
                    "name": "matmulModel_128_64_float_OE_3_2_0.onnx",
                    "signature": "0x425c90287a75f56d68b6ca16a3e8695f"
                }
            ],
            "name": "network",
            "generated_time": "2025-07-25T12:01:30+0200"
        },
        "tools": [
            {
                "name": "ST.EdgeAI.Core",
                "version": "2.1.0-20194 329b0e98d",
                "arguments": "generate --model ownModels/matmulModel_128_64_float/matmulModel_128_64_float.tflite --target stm32n6 --st-neural-art default@user_neuralart_RamOnlyNUCLEO_N6.json --input-data-type float32 -w ownModels/matmulModel_128_64_float/NetworkFiles/ -o ownModels/matmulModel_128_64_float/NetworkFiles/output/",
                "environment": [],
                "input_model": {
                    "model_files": [
                        {
                            "name": "matmulModel_128_64_float.tflite",
                            "signature": "0x7f5d35084b9ffd3c743645bb8eeb775d"
                        }
                    ],
                    "name": "matmulModel_128_64_float",
                    "type": "tflite",
                    "size": 32768,
                    "n_params": 8192
                }
            }
        ],
        "test_name": "",
        "network_signature": "0x6bcb211db73d8c65"
    },
    "model_info": {
        "original_inputs": [
            {
                "name": "serving_default_args_00",
                "data_format": {
                    "type": "FLOAT",
                    "size": 32,
                    "scale": [],
                    "zero": [],
                    "quantizer": "NONE"
                },
                "shape": [
                    1,
                    128
                ],
                "shape_map": [
                    "BATCH",
                    "CH"
                ],
                "c_shape_map": [
                    "BATCH",
                    "CH"
                ]
            }
        ],
        "original_outputs": [
            {
                "name": "gemm_0",
                "data_format": {
                    "type": "FLOAT",
                    "size": 32,
                    "scale": [],
                    "zero": [],
                    "quantizer": "NONE"
                },
                "shape": [
                    1,
                    64
                ],
                "shape_map": [
                    "BATCH",
                    "CH"
                ],
                "c_shape_map": [
                    "BATCH",
                    "CH"
                ]
            }
        ]
    },
    "tensors": {
        "Input_0_out_0": {
            "format": {
                "params": [
                    null,
                    null
                ],
                "class": "float32",
                "type": "FLOAT32"
            },
            "data_channel_position": "CHFIRST",
            "data_channel_batch": 1,
            "user_allocated": false
        },
        "Gemm_1_out_0": {
            "format": {
                "params": [
                    null,
                    null
                ],
                "class": "float32",
                "type": "FLOAT32"
            },
            "data_channel_position": "CHFIRST",
            "data_channel_batch": 1,
            "user_allocated": false
        },
        "Gemm_1_weights": {
            "format": {
                "params": [
                    null,
                    null
                ],
                "class": "float32",
                "type": "FLOAT32"
            }
        }
    },
    "nodes": {
        "Gemm_1": {
            "names": [
                "FULLY_CONNECTED_0"
            ]
        }
    }
}